dragonpg/__init__.py
dragonpg/example.py
dragonpg-1.0.1.dist-info/LICENSE
dragonpg-1.0.1.dist-info/METADATA
dragonpg-1.0.1.dist-info/WHEEL
dragonpg-1.0.1.dist-info/top_level.txt
dragonpg-1.0.1.dist-info/RECORD
