Metadata-Version: 2.1
Name: dragonpg
Version: 1.0.1
Summary: pg dragon สล็อต คาสิโน บาคาร่า ครบจบในเว็บเดียว 24 ชั่วโมง
Author-email: dragonpg <dragonpg@example.com>
Project-URL: Homepage, https://github.com/
Classifier: Programming Language :: Python :: 3
Classifier: License :: OSI Approved :: MIT License
Classifier: Operating System :: OS Independent
Requires-Python: >=3.7
License-File: LICENSE
